pro_sports_transactions/__init__.py
pro_sports_transactions/handlers/__init__.py
pro_sports_transactions/handlers/base_handler.py
pro_sports_transactions/handlers/direct_handler.py
pro_sports_transactions/handlers/unflare_handler.py
pro_sports_transactions/search.py
pro_sports_transactions-1.1.1.dist-info/LICENSE
pro_sports_transactions-1.1.1.dist-info/METADATA
pro_sports_transactions-1.1.1.dist-info/WHEEL
pro_sports_transactions-1.1.1.dist-info/RECORD
