Metadata-Version: 2.3
Name: pro_sports_transactions
Version: 1.1.1
Summary: A Python Library for Consuming Transactions from Pro Sports Transactions (https://www.prosportstransactions.com)
License: MIT
Keywords: api,basketball,baseball,data,data science,draft,fines,football,hockey,injuries,mlb,mls,nba,nfl,nhl,prosports,prosportstransactions,pro sports,pro sports transactions,soccer,sports,stats,trades,transactions
Author: Randy Forbes
Author-email: randy.forbes@gmail.com
Maintainer: Randy Forbes
Maintainer-email: randy.forbes@gmail.com
Requires-Python: >=3.11,<4.0
Classifier: Intended Audience :: Developers
Classifier: Intended Audience :: Science/Research
Classifier: License :: OSI Approved :: MIT License
Classifier: Operating System :: OS Independent
Classifier: Programming Language :: Python :: 3
Classifier: Programming Language :: Python :: 3.11
Classifier: Programming Language :: Python :: 3.12
Classifier: Programming Language :: Python :: 3.13
Classifier: Topic :: Software Development
Requires-Dist: aiohttp (>=3.12.14,<4.0.0)
Requires-Dist: brotli (>=1.0.9,<2.0.0)
Requires-Dist: bs4 (>=0.0.1,<0.0.2)
Requires-Dist: html5lib (>=1.1,<2.0)
Requires-Dist: lxml (>=4.9.2,<5.0.0)
Requires-Dist: pandas (>=2.0.0,<3.0.0)
Project-URL: Documentation, https://github.com/rsforbes/pro_sports_transactions/blob/main/README.md
Project-URL: Repository, https://github.com/rsforbes/pro_sports_transactions
